GridSeisPy/__init__.py
GridSeisPy/grid.py
GridSeisPy/horiz.py
GridSeisPy/keys.py
GridSeisPy/mapping.py
GridSeisPy/seis_data.py
GridSeisPy/settings.py
GridSeisPy/base/__init__.py
GridSeisPy/base/base_class.py
GridSeisPy/base/base_config.py
GridSeisPy/base/base_dl.py
GridSeisPy/base/io.py
GridSeisPy/examples/usage.py
GridSeisPy/ibm2ieee/__init__.py
GridSeisPy/ibm2ieee/ibm2ieee.py
GridSeisPy/ibm2ieee/test/__init__.py
GridSeisPy/ibm2ieee/test/ibm2ieee.py
GridSeisPy/ibm2ieee/test/test_ibm2ieee.py
gridseispy-0.2.245.dist-info/METADATA
gridseispy-0.2.245.dist-info/WHEEL
gridseispy-0.2.245.dist-info/top_level.txt
gridseispy-0.2.245.dist-info/RECORD
