Metadata-Version: 2.4
Name: GridSeisPy
Version: 0.2.245
Summary: A Python library for seismic data processing and visualization.
Author-email: wxiong_swpu <1305483753@qq.com>
Project-URL: Homepage, https://github.com/wxiong_swpu/GridSeisPy
Project-URL: Bug Tracker, https://github.com/wxiong_swpu/GridSeisPy/issues
Classifier: Programming Language :: Python :: 3
Classifier: License :: OSI Approved :: MIT License
Classifier: Operating System :: OS Independent
Classifier: Topic :: Scientific/Engineering :: Physics
Requires-Python: >=3.11
Requires-Dist: numpy
Requires-Dist: numba
Requires-Dist: rich
Requires-Dist: chardet
Requires-Dist: matplotlib
Requires-Dist: scipy
Requires-Dist: pyvista
